setup.py
powertop/__init__.py
powertop/__main__.py
powertop/decoder.py
powertop.egg-info/PKG-INFO
powertop.egg-info/SOURCES.txt
powertop.egg-info/dependency_links.txt
powertop.egg-info/top_level.txt