Metadata-Version: 1.1
Name: powertop
Version: 0.2.1
Summary: Small wrapper to use PowerTOP in Python
Home-page: https://github.com/ProgVal/python-powertop
Author: Valentin Lorentz
Author-email: valentin.lorentz+git@ens-lyon.org
License: UNKNOWN
Platform: UNKNOWN
Classifier: Development Status :: 1 - Planning
Classifier: Intended Audience :: Developers
Classifier: License :: OSI Approved :: MIT License
Classifier: Operating System :: POSIX :: Linux
Classifier: Programming Language :: Python :: 3
Classifier: Topic :: System :: Monitoring
